zdcode/__init__.py
zdcode/__main__.py
zdcode/bundle.py
zdcode/program.py
zdcode/zake.py
zdcode/zdlexer.py
zdcode-2.13.7.dist-info/LICENSE.md
zdcode-2.13.7.dist-info/METADATA
zdcode-2.13.7.dist-info/WHEEL
zdcode-2.13.7.dist-info/entry_points.txt
zdcode-2.13.7.dist-info/RECORD
